odoo/addons/mail_template_category/__init__.py
odoo/addons/mail_template_category/__manifest__.py
odoo/addons/mail_template_category/i18n/es.po
odoo/addons/mail_template_category/i18n/mail_template_category.pot
odoo/addons/mail_template_category/models/__init__.py
odoo/addons/mail_template_category/models/mail_template.py
odoo/addons/mail_template_category/models/mail_template_category.py
odoo/addons/mail_template_category/security/ir.model.access.csv
odoo/addons/mail_template_category/views/mail_template.xml
odoo/addons/mail_template_category/views/mail_template_category.xml
odoo_addon_mail_template_category-16.0.1.0.0.dist-info/METADATA
odoo_addon_mail_template_category-16.0.1.0.0.dist-info/WHEEL
odoo_addon_mail_template_category-16.0.1.0.0.dist-info/top_level.txt
odoo_addon_mail_template_category-16.0.1.0.0.dist-info/RECORD
